freenove/_init_.py
freenove/freenove.py
freenove-0.0.14.data/data/requirements.txt
freenove-0.0.14.dist-info/licenses/LICENSE.txt
freenove-0.0.14.dist-info/METADATA
freenove-0.0.14.dist-info/WHEEL
freenove-0.0.14.dist-info/top_level.txt
freenove-0.0.14.dist-info/RECORD
