Metadata-Version: 2.4
Name: freenove
Version: 0.0.14
Summary: freenove_config
Author: syc
Author-email: 1318270340@qq.com
Requires-Python: >=3.6
License-File: LICENSE.txt
Dynamic: author
Dynamic: author-email
Dynamic: description
Dynamic: description-content-type
Dynamic: license-file
Dynamic: requires-python
Dynamic: summary
